[
  {
    "legoID": "75390",
    "ownerName": "ssilva1977",
    "ownerProfileLink": "https://www.vinted.fr/member/80722302-ssilva1977",
    "productImage": "https://marketplace-web-assets.vinted.com/assets/no-photo/user-empty-state.svg",
    "productLink": "https://www.vinted.fr/items/5572728004-lego-star-wars-75390-robo-x-wing-de-luke-skywalker?referrer=catalog",
    "price": "12,00 €",
    "title": "LEGO",
    "size": "Taille unique",
    "likes": 4
  },
  {
    "legoID": "75390",
    "ownerName": "nadine111943",
    "ownerProfileLink": "https://www.vinted.fr/member/68501837-nadine111943",
    "productImage": "https://marketplace-web-assets.vinted.com/assets/no-photo/user-empty-state.svg",
    "productLink": "https://www.vinted.fr/items/5558922116-lego-75390-star-wars-le-robot-x-wing-de-luke-skywalker?referrer=catalog",
    "price": "11,00 €",
    "title": "LEGO",
    "size": "7 ans / 122 cm",
    "likes": 8
  },
  {
    "legoID": "75390",
    "ownerName": "theodore68",
    "ownerProfileLink": "https://www.vinted.fr/member/16818884-theodore68",
    "productImage": "https://images1.vinted.net/t/03_025d8_SPXdJwvuchVFQKe5Fu3ncqZw/50x50/1652852097.jpeg?s=670c6106537192054c8ef8ce1bae58a0b45571d7",
    "productLink": "https://www.vinted.fr/items/5564052287-lego-star-wars-75390?referrer=catalog",
    "price": "15,00 €",
    "title": "LEGO",
    "size": "6 ans / 116 cm",
    "likes": 3
  },
  {
    "legoID": "75390",
    "ownerName": "audrey76290",
    "ownerProfileLink": "https://www.vinted.fr/member/152010802-audrey76290",
    "productImage": "https://marketplace-web-assets.vinted.com/assets/no-photo/user-empty-state.svg",
    "productLink": "https://www.vinted.fr/items/5188548539-lego-star-wars?referrer=catalog",
    "price": "10,00 €",
    "title": "LEGO Star Wars",
    "size": "6 ans / 116 cm",
    "likes": 8
  },
  {
    "legoID": "75390",
    "ownerName": "kleuhp",
    "ownerProfileLink": "https://www.vinted.fr/member/46392307-kleuhp",
    "productImage": "https://marketplace-web-assets.vinted.com/assets/no-photo/user-empty-state.svg",
    "productLink": "https://www.vinted.fr/items/5154774224-lego-star-wars-75390-luke-skywalker?referrer=catalog",
    "price": "11,00 €",
    "title": "LEGO",
    "size": "Taille unique",
    "likes": 10
  },
  {
    "legoID": "75390",
    "ownerName": "damss69003",
    "ownerProfileLink": "https://www.vinted.fr/member/42719339-damss69003",
    "productImage": "https://images1.vinted.net/t/01_0183d_6Dz6NXsT357mXVUNthcUQy1o/50x50/1603807405.jpeg?s=9149f5ed4ab4d783c8f839405f83ef7004989a25",
    "productLink": "https://www.vinted.fr/items/5482667477-lego-star-wars-75390?referrer=catalog",
    "price": "10,00 €",
    "title": "LEGO",
    "size": "5 ans / 110 cm",
    "likes": 4
  },
  {
    "legoID": "75390",
    "ownerName": "kristian3318",
    "ownerProfileLink": "https://www.vinted.fr/member/162469615-kristian3318",
    "productImage": "https://images1.vinted.net/t/01_0170f_H7m5t3fSzfYHLmoxkCw8aQC5/50x50/1695306958.jpeg?s=37c2e88a84f74dd407f4986e209193320d4cfea9",
    "productLink": "https://www.vinted.fr/items/5562285691-lego-star-wars-75390?referrer=catalog",
    "price": "12,00 €",
    "title": "LEGO",
    "size": "6-9 mois / 68 cm",
    "likes": 3
  },
  {
    "legoID": "75390",
    "ownerName": "tresorschafouinolaf",
    "ownerProfileLink": "https://www.vinted.fr/member/75790857-tresorschafouinolaf",
    "productImage": "https://images1.vinted.net/t/03_01c15_RjbQd7XzVTwVeUKjFMkpiiM7/50x50/1638692043.jpeg?s=c624f149948cea3f19a5fd72c2bc87d28c874b99",
    "productLink": "https://www.vinted.fr/items/5556086465-robot-x-wing-mech-luke-skywalker-75390-star-wars-lego?referrer=catalog",
    "price": "14,00 €",
    "title": "LEGO",
    "size": "Taille unique",
    "likes": 3
  },
  {
    "legoID": "75390",
    "ownerName": "simao_mendes12",
    "ownerProfileLink": "https://www.vinted.fr/member/239807432-simaomendes12",
    "productImage": "https://images1.vinted.net/t/04_00465_3jb1Wwc9Et85GUnP6mR382Re/50x50/1732911343.jpeg?s=5dcc2f30e6069c888bbd9c8d82972685b2defc11",
    "productLink": "https://www.vinted.fr/items/5539659318-lego-75390?referrer=catalog",
    "price": "15,00 €",
    "title": "LEGO",
    "size": "Taille unique",
    "likes": null
  },
  {
    "legoID": "75390",
    "ownerName": "goprevox",
    "ownerProfileLink": "https://www.vinted.fr/member/36211305-goprevox",
    "productImage": "https://images1.vinted.net/t/03_01276_RNGQ9hZrUNNoYHSjWFeL72fS/50x50/1726486178.jpeg?s=3ab59111f40bd1104caaa697a1993fb7c1eeb0ee",
    "productLink": "https://www.vinted.fr/items/5432660528-lego-stars-wars-75390-neuf?referrer=catalog",
    "price": "12,00 €",
    "title": "LEGO",
    "size": "Taille unique",
    "likes": null
  },
  {
    "legoID": "75390",
    "ownerName": "bagunssa",
    "ownerProfileLink": "https://www.vinted.fr/member/63481130-bagunssa",
    "productImage": "https://images1.vinted.net/t/03_00f58_YC6EvkXYMM4gw4h2e7GVvtxD/50x50/1730578962.jpeg?s=0b6dc7bbc12adc5ea8403f1f095c667d1d2cf956",
    "productLink": "https://www.vinted.fr/items/5492840325-lego-star-wars-75390?referrer=catalog",
    "price": "13,00 €",
    "title": "LEGO",
    "size": "6 ans / 116 cm",
    "likes": 10
  },
  {
    "legoID": "75390",
    "ownerName": "ingridhe76260",
    "ownerProfileLink": "https://www.vinted.fr/member/34101806-ingridhe76260",
    "productImage": "https://marketplace-web-assets.vinted.com/assets/no-photo/user-empty-state.svg",
    "productLink": "https://www.vinted.fr/items/5544383723-star-wars?referrer=catalog",
    "price": "17,00 €",
    "title": "LEGO",
    "size": "6 ans / 116 cm",
    "likes": 1
  },
  {
    "legoID": "75390",
    "ownerName": "jin3154",
    "ownerProfileLink": "https://www.vinted.fr/member/119115117-jin3154",
    "productImage": "https://images1.vinted.net/t/01_01294_PqLK4YLLuJsoaNEtTA9wKEes/50x50/1668209887.jpeg?s=4156be6dd766f0330718238b2d88249de4fd7539",
    "productLink": "https://www.vinted.fr/items/5471539690-lego-starwars-75390-novo-e-selado?referrer=catalog",
    "price": "13,00 €",
    "title": "LEGO",
    "size": "Taille unique",
    "likes": 7
  },
  {
    "legoID": "75390",
    "ownerName": "djnachtaktiv",
    "ownerProfileLink": "https://www.vinted.fr/member/246626431-djnachtaktiv",
    "productImage": "https://images1.vinted.net/t/01_01d58_6wabkmKiN5CtAbskAiCie9Lj/50x50/1734110774.jpeg?s=930b1965b43d3c405752d732c528365d323707c2",
    "productLink": "https://www.vinted.fr/items/5565419006-lego-75390-star-wars-luke-skywalker?referrer=catalog",
    "price": "17,00 €",
    "title": "LEGO",
    "size": "Taille unique",
    "likes": 19
  },
  {
    "legoID": "75390",
    "ownerName": "sirhexoludio",
    "ownerProfileLink": "https://www.vinted.fr/member/153301785-sirhexoludio",
    "productImage": "https://images1.vinted.net/t/04_0040d_VSX8SfYm7rpjMYbCxNecadLP/50x50/1735211597.jpeg?s=41081525375332f547a6c3a746e883cc2ca64010",
    "productLink": "https://www.vinted.fr/items/5573722319-75390-lego-star-wars-luke-skywalker-x-wing?referrer=catalog",
    "price": "20,00 €",
    "title": "LEGO Star Wars",
    "size": "Taille unique",
    "likes": 1
  },
  {
    "legoID": "75390",
    "ownerName": "petrabecue",
    "ownerProfileLink": "https://www.vinted.fr/member/193811092-petrabecue",
    "productImage": "https://images1.vinted.net/t/01_012de_QjZFn9bPAdXnY6VXNbo3enoW/50x50/1721324407.jpeg?s=bafb7f36ab5353efed2f475478845a1ff50dc20b",
    "productLink": "https://www.vinted.fr/items/5506105229-lego-star-wars-75390?referrer=catalog",
    "price": "10,00 €",
    "title": "LEGO",
    "size": "Taille unique",
    "likes": null
  },
  {
    "legoID": "75390",
    "ownerName": "kusanagiriku",
    "ownerProfileLink": "https://www.vinted.fr/member/66888718-kusanagiriku",
    "productImage": "https://images1.vinted.net/t/03_00659_yz4Mp4T4dT97xs64uz6dau4y/50x50/1629471428.jpeg?s=6dfd3aba60ad2caaf11eac312294736c9103e1d4",
    "productLink": "https://www.vinted.fr/items/5550503510-lego-star-wars-75309-luke-skywalker?referrer=catalog",
    "price": "10,00 €",
    "title": "LEGO",
    "size": "Prématuré, jusqu'à 44cm",
    "likes": 1
  },
  {
    "legoID": "75390",
    "ownerName": "andre3992",
    "ownerProfileLink": "https://www.vinted.fr/member/106686308-andre3992",
    "productImage": "https://images1.vinted.net/t/02_0116b_kbvbFUmySZssPboFMiCjAPZ6/50x50/1662322500.jpeg?s=eb0cd6419c8dcc4c785acf31daf1b6c88c36f86c",
    "productLink": "https://www.vinted.fr/items/5354673878-lego-star-wars-75390?referrer=catalog",
    "price": "12,00 €",
    "title": "Star Wars",
    "size": "Naissance / 44 cm",
    "likes": 3
  },
  {
    "legoID": "75390",
    "ownerName": "jorandall62",
    "ownerProfileLink": "https://www.vinted.fr/member/23806632-jorandall62",
    "productImage": "https://images1.vinted.net/t/02_01c12_3VJmmsqepuXVWf7hxpeHpZKx/50x50/1605229897.jpeg?s=dcdf53a1f96859663f193a741fdd8991d566df52",
    "productLink": "https://www.vinted.fr/items/3941086617-45-tours-lionel-hampton-jazz-de-poche-n-10?referrer=catalog",
    "price": "5,00 €",
    "title": "45 tours Lionel Hampton jazz de poche n 10",
    "size": "Bon état",
    "likes": 1
  },
  {
    "legoID": "75390",
    "ownerName": "schyla89",
    "ownerProfileLink": "https://www.vinted.fr/member/48465506-schyla89",
    "productImage": "https://images1.vinted.net/t/03_016c7_56ZmjMCrtV4W9mmMUC7vyLZd/50x50/1725570331.jpeg?s=26c26e2498162408235f40084b590ef03ab3009a",
    "productLink": "https://www.vinted.fr/items/5520064695-lego-star-wars?referrer=catalog",
    "price": "35,00 €",
    "title": "LEGO",
    "size": "6 ans / 116 cm",
    "likes": 13
  },
  {
    "legoID": "75390",
    "ownerName": "tara-bricks",
    "ownerProfileLink": "https://www.vinted.fr/member/225779075-tara-bricks",
    "productImage": "https://images1.vinted.net/t/02_00ca6_nVCMrm6jcX1jN1pLcDdjSfQB/50x50/1725110234.jpeg?s=3ef3f7f126686733553da3fa5dbbf0623a0f17f3",
    "productLink": "https://www.vinted.fr/items/5150477064-lego-star-wars-75390-luke-skywalker-x-wing-mecha?referrer=catalog",
    "price": "12,50 €",
    "title": "LEGO Star Wars",
    "size": "24-36 mois / 92 cm",
    "likes": 7
  },
  {
    "legoID": "75390",
    "ownerName": "naddi-29-01-88",
    "ownerProfileLink": "https://www.vinted.fr/member/43161164-naddi-29-01-88",
    "productImage": "https://images1.vinted.net/t/02_021c4_Vfg6AUofqPcKv5CH1ynvWxyr/50x50/1605962267.jpeg?s=139e1f4b2cd0a68127fdb82ce4abf16c21a440ae",
    "productLink": "https://www.vinted.fr/items/5436589176-star-wars-set-75390-neu?referrer=catalog",
    "price": "10,00 €",
    "title": "LEGO",
    "size": "Taille unique",
    "likes": 4
  },
  {
    "legoID": "75390",
    "ownerName": "tawa82",
    "ownerProfileLink": "https://www.vinted.fr/member/72306508-tawa82",
    "productImage": "https://images1.vinted.net/t/03_01ac6_owa9cCUXwsF4DZUa3nqHRptG/50x50/1637067100.jpeg?s=a9ec26cdb580cb23568f73f27d46ad1a55bb8c5f",
    "productLink": "https://www.vinted.fr/items/4917739095-lego-star-wars-pack-x3-753687537075390-16off?referrer=catalog",
    "price": "40,00 €",
    "title": "LEGO",
    "size": "Taille unique",
    "likes": 8
  },
  {
    "legoID": "75390",
    "ownerName": "nina.schwartner",
    "ownerProfileLink": "https://www.vinted.fr/member/44978805-ninaschwartner",
    "productImage": "https://images1.vinted.net/t/01_01036_1yccre43BWMsNVG7vtDiyye5/50x50/1673465166.jpeg?s=ece456d1c67d3b2b1a34ddc226b8a05185336df5",
    "productLink": "https://www.vinted.fr/items/5523886707-lego-75390-star-wars?referrer=catalog",
    "price": "8,00 €",
    "title": "LEGO",
    "size": "Taille unique",
    "likes": null
  },
  {
    "legoID": "75390",
    "ownerName": "rayo63",
    "ownerProfileLink": "https://www.vinted.fr/member/223524709-rayo63",
    "productImage": "https://images1.vinted.net/t/03_0218a_JrZsz1oRnD8fMZNRprCdnqZj/50x50/1724101657.jpeg?s=e927b7ea844f87c1f44ff1bafd6acca0c8439139",
    "productLink": "https://www.vinted.fr/items/5370363784-lote-star-wars-lego-nuevo?referrer=catalog",
    "price": "35,00 €",
    "title": "LEGO",
    "size": "Taille unique",
    "likes": 3
  },
  {
    "legoID": "75390",
    "ownerName": "luiscasto",
    "ownerProfileLink": "https://www.vinted.fr/member/85419356-luiscasto",
    "productImage": "https://images1.vinted.net/t/01_006aa_HGXhn4Q82XwJfUbvctJEjLNW/50x50/1648380573.jpeg?s=fc56c5ba3d42278e62f2c73367d8a6d6418db0a2",
    "productLink": "https://www.vinted.fr/items/5313800635-lego-starwars-75390?referrer=catalog",
    "price": "11,00 €",
    "title": "LEGO",
    "size": "Neuf sans étiquette",
    "likes": 1
  },
  {
    "legoID": "75390",
    "ownerName": "emilio8719",
    "ownerProfileLink": "https://www.vinted.fr/member/159889083-emilio8719",
    "productImage": "https://images1.vinted.net/t/01_00fbd_r8EqA2wtszga81SeMdKh8EJ8/50x50/1708927106.jpeg?s=3b390ebc1672c8c2fa2beb82f7663d2806068029",
    "productLink": "https://www.vinted.fr/items/4668835517-10-minifiguras-lego-original?referrer=catalog",
    "price": "45,00 €",
    "title": "Original",
    "size": "Neuf sans étiquette",
    "likes": 13
  },
  {
    "legoID": "75390",
    "ownerName": "neatbones",
    "ownerProfileLink": "https://www.vinted.fr/member/53139635-neatbones",
    "productImage": "https://images1.vinted.net/t/02_0268e_CfS7Eh4TJqHCQKxzGcXEMTLu/50x50/1725103638.jpeg?s=e671a76b0ccdf48ee8841aea676257afe5a7d08b",
    "productLink": "https://www.vinted.fr/items/5533824897-4-lego-star-wars-mech?referrer=catalog",
    "price": "60,00 €",
    "title": "LEGO",
    "size": "Taille unique",
    "likes": 1
  },
  {
    "legoID": "75390",
    "ownerName": "suithorien",
    "ownerProfileLink": "https://www.vinted.fr/member/129141117-suithorien",
    "productImage": "https://images1.vinted.net/t/03_023f5_bjjnqmMWKKexb1KKpNfKENcZ/50x50/1674166752.jpeg?s=87bd9e4beac1694fc4d5b38c05484b8bc04ad58d",
    "productLink": "https://www.vinted.fr/items/5568555401-lego-star-wars-75368-75369-75370-75390?referrer=catalog",
    "price": "56,00 €",
    "title": "LEGO Star Wars",
    "size": "Taille unique",
    "likes": 1
  },
  {
    "legoID": "75390",
    "ownerName": "gabripit",
    "ownerProfileLink": "https://www.vinted.fr/member/151496333-gabripit",
    "productImage": "https://images1.vinted.net/t/03_01e49_THUxLyswA2Vr1GFaXHgFFz3Z/50x50/1717694213.jpeg?s=c1fba566a7170f704ab7746f9f7f73ce478acd51",
    "productLink": "https://www.vinted.fr/items/4746094313-legor-star-wars-75050-b-wing?referrer=catalog",
    "price": "75,00 €",
    "title": "LEGO",
    "size": "Taille unique",
    "likes": 10
  },
  {
    "legoID": "75390",
    "ownerName": "luiscasto",
    "ownerProfileLink": "https://www.vinted.fr/member/85419356-luiscasto",
    "productImage": "https://images1.vinted.net/t/01_006aa_HGXhn4Q82XwJfUbvctJEjLNW/50x50/1648380573.jpeg?s=fc56c5ba3d42278e62f2c73367d8a6d6418db0a2",
    "productLink": "https://www.vinted.fr/items/5314813746-lego-set-2-unid-dark-vader-luke?referrer=catalog",
    "price": "35,00 €",
    "title": "LEGO",
    "size": "Neuf sans étiquette",
    "likes": null
  },
  {
    "legoID": "75390",
    "ownerName": "sdg130478",
    "ownerProfileLink": "https://www.vinted.fr/member/53919918-sdg130478",
    "productImage": "https://images1.vinted.net/t/02_0091a_xQPuHqQqq1FD2Z1BJ5xJZQvD/50x50/1718176438.jpeg?s=04e46aa6d43b758e75858e41cdbfa59fdd92e8ba",
    "productLink": "https://www.vinted.fr/items/4566920851-legor-star-wars-75390-und-75373?referrer=catalog",
    "price": "55,00 €",
    "title": "Star Wars",
    "size": "M",
    "likes": 1
  },
  {
    "legoID": "75390",
    "ownerName": "rav6442",
    "ownerProfileLink": "https://www.vinted.fr/member/70858415-rav6442",
    "productImage": "https://images1.vinted.net/t/02_0151e_szEU6bsEULKDYDuo7mBpzCBs/50x50/1703663899.jpeg?s=4d68b9da6acb5710d20b10f971d4c4242d609a10",
    "productLink": "https://www.vinted.fr/items/5497669532-battle-packs-lego-star-wars-mandalorian-skywalker-mech?referrer=catalog",
    "price": "99,99 €",
    "title": "LEGO",
    "size": "Prématuré, jusqu'à 44cm",
    "likes": 3
  },
  {
    "legoID": "75390",
    "ownerName": "gabripit",
    "ownerProfileLink": "https://www.vinted.fr/member/151496333-gabripit",
    "productImage": "https://images1.vinted.net/t/03_01e49_THUxLyswA2Vr1GFaXHgFFz3Z/50x50/1717694213.jpeg?s=c1fba566a7170f704ab7746f9f7f73ce478acd51",
    "productLink": "https://www.vinted.fr/items/4907250505-legor-star-wars-75055-imperial-star-destroyer?referrer=catalog",
    "price": "163,00 €",
    "title": "LEGO",
    "size": "Taille unique",
    "likes": 8
  }
]